{
    "url": {
        "data": "http:\/\/cdcb.judicial.gov.tw\/abbs\/wkw\/WHD6K03.jsp?ab=AAAdkxAAHAAAMARAAK&bc=105&cd=%AA%6B%B5%6E%AA%C0++++++++++++++&de=000078&ef=KSD&fg=1",
        "staff": "http:\/\/cdcb.judicial.gov.tw\/abbs\/wkw\/WHD6K04.jsp?ab=AAAdkxAAHAAAMARAAK&bc=105&cd=%AA%6B%B5%6E%AA%C0++++++++++++++&de=000078&ef=KSD&fg=1",
        "office": "http:\/\/cdcb.judicial.gov.tw\/abbs\/wkw\/WHD6K07.jsp?ab=AAAdkxAAHAAAMARAAK&bc=105&cd=%AA%6B%B5%6E%AA%C0++++++++++++++&de=000078&ef=KSD&fg=1"
    },
    "登記案號": "105年法登社字78號",
    "類別": "社團",
    "案由": "設立登記",
    "主任": "陳錦鑾",
    "登記號數": "1750",
    "收件日期": "105\/12\/07",
    "登記日期": "105\/12\/08",
    "公告日期": "105\/12\/12",
    "登記簿": "36冊29頁",
    "任期判定": "",
    "屆期判定": "",
    "法人代表": "理事長",
    "法人名稱": "社團法人中華國際專業語言發展協會",
    "設立登記日期": "105\/12\/08",
    "主事務所": "高雄市小港區桂園路53號",
    "目的": "以配合政府政策，整合社會資源，協助培訓人才，提高語言專業能力，提高企業競爭力為宗旨。",
    "捐助方法": "會費及捐款等",
    "許可機關日期": "內政部105年8月19日台內團字第1050048774號函",
    "存立時期": "永久",
    "財產總額": "10000",
    "結案原因": "准許",
    "結案日期": "105\/12\/09",
    "歸檔日期": "",
    "發證日期": "",
    "送達代收人姓名": "",
    "送達代收人住址": "",
    "郵遞區號": "",
    "清算人": "",
    "註銷日期": "",
    "撤銷日期": "",
    "撤(註)銷機關文號": "",
    "撤(註)銷原因": "",
    "董監事": [
        [
            "理事長",
            "張文晃"
        ],
        [
            "常務理事",
            "張欣釗"
        ],
        [
            "常務理事",
            "鄭錡璉"
        ],
        [
            "理事",
            "陳婉菱"
        ],
        [
            "理事",
            "張培絹"
        ],
        [
            "理事",
            "黃安婷"
        ],
        [
            "理事",
            "郭雅芸"
        ],
        [
            "理事",
            "林篍山"
        ],
        [
            "理事",
            "吳怡靜"
        ],
        [
            "常務監事",
            "黃之盈"
        ],
        [
            "監事",
            "莊雅淳"
        ],
        [
            "監事",
            "魏妙姍"
        ]
    ],
    "分事務所": [],
    "latitude": "",
    "longitude": ""
}