{
    "url": {
        "data": "http:\/\/cdcb.judicial.gov.tw\/abbs\/wkw\/WHD6K03.jsp?ab=AAAdkxAAHAAAMDrAAI&bc=106&cd=%AA%6B%B5%6E%AA%C0++++++++++++++&de=000002&ef=KSD&fg=1",
        "staff": "http:\/\/cdcb.judicial.gov.tw\/abbs\/wkw\/WHD6K04.jsp?ab=AAAdkxAAHAAAMDrAAI&bc=106&cd=%AA%6B%B5%6E%AA%C0++++++++++++++&de=000002&ef=KSD&fg=1",
        "office": "http:\/\/cdcb.judicial.gov.tw\/abbs\/wkw\/WHD6K07.jsp?ab=AAAdkxAAHAAAMDrAAI&bc=106&cd=%AA%6B%B5%6E%AA%C0++++++++++++++&de=000002&ef=KSD&fg=1"
    },
    "登記案號": "106年法登社字2號",
    "類別": "社團",
    "案由": "設立登記",
    "主任": "陳錦鑾",
    "登記號數": "1756",
    "收件日期": "106\/02\/02",
    "登記日期": "106\/02\/07",
    "公告日期": "106\/02\/08",
    "登記簿": "36冊35頁",
    "任期判定": "",
    "屆期判定": "",
    "法人代表": "理事長",
    "法人名稱": "社團法人高雄市漁船船員服務促進協會",
    "設立登記日期": "106\/02\/07",
    "主事務所": "高雄市鎮區一心一路239號4樓之1",
    "目的": "本會以配合政府部門解決船員與船主的勞資糾紛、促進船員基本權益的維護、擴增本國漁船僱用船員的途徑、協助勞資雙方訂定合理的契約為宗旨。",
    "捐助方法": "會費及捐款等。",
    "許可機關日期": "98年8月26日高雄市政府社會局一字第0980039405號函。",
    "存立時期": "永久",
    "財產總額": "13406",
    "結案原因": "准許",
    "結案日期": "106\/02\/07",
    "歸檔日期": "",
    "發證日期": "",
    "送達代收人姓名": "",
    "送達代收人住址": "",
    "郵遞區號": "",
    "清算人": "",
    "註銷日期": "",
    "撤銷日期": "",
    "撤(註)銷機關文號": "",
    "撤(註)銷原因": "",
    "董監事": [
        [
            "理事長",
            "謝錫祥"
        ],
        [
            "常務理事",
            "呂德立"
        ],
        [
            "常務理事",
            "王志邦"
        ],
        [
            "理事",
            "陳春木"
        ],
        [
            "理事",
            "陳燕梅"
        ],
        [
            "理事",
            "馬振斌"
        ],
        [
            "理事",
            "吳昌佩"
        ],
        [
            "理事",
            "盧天德"
        ],
        [
            "理事",
            "宋承厚"
        ],
        [
            "常務監事",
            "鄭鋒興"
        ],
        [
            "監事",
            "蔡宗翰"
        ],
        [
            "監事",
            "楊朝富"
        ]
    ],
    "分事務所": [],
    "latitude": "",
    "longitude": ""
}